iag_sdk/__init__.py
iag_sdk/client.py
iag_sdk/client_base.py
iag_sdk/models.py
iag_sdk/modules/__init__.py
iag_sdk/modules/accounts.py
iag_sdk/modules/collections.py
iag_sdk/modules/config.py
iag_sdk/modules/devices.py
iag_sdk/modules/groups.py
iag_sdk/modules/http_requests.py
iag_sdk/modules/inventory.py
iag_sdk/modules/ldap.py
iag_sdk/modules/modules.py
iag_sdk/modules/netconf.py
iag_sdk/modules/netmiko.py
iag_sdk/modules/nornir.py
iag_sdk/modules/password_reset.py
iag_sdk/modules/playbooks.py
iag_sdk/modules/pronghorn.py
iag_sdk/modules/rbac.py
iag_sdk/modules/roles.py
iag_sdk/modules/scripts.py
iag_sdk/modules/secrets.py
iag_sdk/modules/security_questions.py
iag_sdk/modules/system.py
iag_sdk/modules/terraforms.py
iag_sdk/modules/user_schema.py
iag_sdk-2024.1b2.dist-info/LICENSE
iag_sdk-2024.1b2.dist-info/METADATA
iag_sdk-2024.1b2.dist-info/WHEEL
iag_sdk-2024.1b2.dist-info/top_level.txt
iag_sdk-2024.1b2.dist-info/RECORD
