Metadata-Version: 2.1
Name: iag_sdk
Version: 2024.1b2
Summary: Lightweight SDK to simplify the process of interacting with the Itential Automation Gateway API.
Home-page: https://github.com/awetomate/itential-iag-sdk
Author: John Frauchiger
Author-email: john@awetomate.net
License: MIT
Project-URL: Documentation, https://github.com/awetomate/itential-iag-sdk
Project-URL: Source, https://github.com/awetomate/itential-iag-sdk
Classifier: Development Status :: 4 - Beta
Classifier: Intended Audience :: Developers
Classifier: Intended Audience :: Information Technology
Classifier: License :: OSI Approved :: MIT License
Classifier: Operating System :: OS Independent
Classifier: Programming Language :: Python :: 3.9
Classifier: Programming Language :: Python :: 3.10
Classifier: Programming Language :: Python :: 3.11
Classifier: Programming Language :: Python :: 3.12
Classifier: Topic :: Utilities
Requires-Python: >=3.9,<3.12
License-File: LICENSE
Requires-Dist: requests
Requires-Dist: pydantic <3.0.0,>=2.5.0
